git_substatus/__init__.py
git_substatus/__main__.py
git_substatus/branch.py
git_substatus/cmdline.py
git_substatus/directory.py
git_substatus/fetch.py
git_substatus/gitsubstatus.py
git_substatus/numstatus.py
git_substatus/repository.py
git_substatus/stash.py
git_substatus/status.py
git_substatus/utils.py
git_substatus/worktree.py
git_substatus-0.2.11.dist-info/LICENSE
git_substatus-0.2.11.dist-info/METADATA
git_substatus-0.2.11.dist-info/WHEEL
git_substatus-0.2.11.dist-info/entry_points.txt
git_substatus-0.2.11.dist-info/top_level.txt
git_substatus-0.2.11.dist-info/RECORD
