Metadata-Version: 2.1
Name: git-substatus
Version: 0.2.11
Summary: Display the 'git status' in sub-directories
Home-page: https://github.com/strboul/git-substatus
Author: Metin Yazici
License: MIT
Keywords: git sub status fetch directory folder
Classifier: Development Status :: 4 - Beta
Classifier: Environment :: Console
Classifier: Intended Audience :: Developers
Classifier: Intended Audience :: System Administrators
Classifier: License :: OSI Approved :: GNU General Public License v3 (GPLv3)
Classifier: Operating System :: MacOS
Classifier: Operating System :: Microsoft :: Windows
Classifier: Operating System :: POSIX :: Linux
Classifier: Programming Language :: Python :: 3.10
Requires-Python: >=3.10
License-File: LICENSE
